rated/__init__.py
rated/decorators.py
rated/signals.py
django_rated-2.0.0.dist-info/LICENSE
django_rated-2.0.0.dist-info/METADATA
django_rated-2.0.0.dist-info/WHEEL
django_rated-2.0.0.dist-info/top_level.txt
django_rated-2.0.0.dist-info/RECORD
