Metadata-Version: 2.1
Name: django-rated
Version: 2.0.0
Summary: A rate limiting decorator for Django
Author-email: Curtis Maloney <curtis@tinbrain.net>
License: Copyright (c) 2012-2013, Curtis Maloney and individual contributors.
Project-URL: Repository, https://github.com/funkybob/django-rated
Keywords: django,api
Classifier: Environment :: Web Environment
Classifier: Framework :: Django
Classifier: License :: OSI Approved :: BSD License
Classifier: Operating System :: OS Independent
Classifier: Programming Language :: Python
License-File: LICENSE
Requires-Dist: Django >=1.9
Requires-Dist: redis >=2.7.2
Provides-Extra: test
Requires-Dist: pylint ; extra == 'test'
Requires-Dist: isort ; extra == 'test'
Requires-Dist: pytest ; extra == 'test'
Requires-Dist: pytest-django ; extra == 'test'
Requires-Dist: factory-boy ; extra == 'test'
Requires-Dist: pytest-cov ; extra == 'test'
Requires-Dist: pylint-pytest ; extra == 'test'
